notebooklm_tools/__init__.py
notebooklm_tools/cli/__init__.py
notebooklm_tools/cli/ai_docs.py
notebooklm_tools/cli/formatters.py
notebooklm_tools/cli/main.py
notebooklm_tools/cli/utils.py
notebooklm_tools/cli/commands/__init__.py
notebooklm_tools/cli/commands/alias.py
notebooklm_tools/cli/commands/chat.py
notebooklm_tools/cli/commands/config.py
notebooklm_tools/cli/commands/download.py
notebooklm_tools/cli/commands/export.py
notebooklm_tools/cli/commands/note.py
notebooklm_tools/cli/commands/notebook.py
notebooklm_tools/cli/commands/repl.py
notebooklm_tools/cli/commands/research.py
notebooklm_tools/cli/commands/share.py
notebooklm_tools/cli/commands/skill.py
notebooklm_tools/cli/commands/source.py
notebooklm_tools/cli/commands/studio.py
notebooklm_tools/cli/commands/verbs.py
notebooklm_tools/core/__init__.py
notebooklm_tools/core/alias.py
notebooklm_tools/core/auth.py
notebooklm_tools/core/auth_cli.py
notebooklm_tools/core/base.py
notebooklm_tools/core/client.py
notebooklm_tools/core/constants.py
notebooklm_tools/core/conversation.py
notebooklm_tools/core/data_types.py
notebooklm_tools/core/download.py
notebooklm_tools/core/errors.py
notebooklm_tools/core/exceptions.py
notebooklm_tools/core/exports.py
notebooklm_tools/core/models.py
notebooklm_tools/core/notebooks.py
notebooklm_tools/core/notes.py
notebooklm_tools/core/research.py
notebooklm_tools/core/sharing.py
notebooklm_tools/core/sources.py
notebooklm_tools/core/studio.py
notebooklm_tools/core/utils.py
notebooklm_tools/data/AGENTS_SECTION.md
notebooklm_tools/data/SKILL.md
notebooklm_tools/data/references/command_reference.md
notebooklm_tools/data/references/troubleshooting.md
notebooklm_tools/data/references/workflows.md
notebooklm_tools/mcp/__init__.py
notebooklm_tools/mcp/server.py
notebooklm_tools/mcp/tools/__init__.py
notebooklm_tools/mcp/tools/_utils.py
notebooklm_tools/mcp/tools/auth.py
notebooklm_tools/mcp/tools/chat.py
notebooklm_tools/mcp/tools/downloads.py
notebooklm_tools/mcp/tools/exports.py
notebooklm_mcp_cli-0.2.10.dist-info/METADATA
notebooklm_mcp_cli-0.2.10.dist-info/WHEEL
notebooklm_mcp_cli-0.2.10.dist-info/entry_points.txt
notebooklm_mcp_cli-0.2.10.dist-info/licenses/LICENSE
notebooklm_mcp_cli-0.2.10.dist-info/RECORD
