Metadata-Version: 2.4
Name: notebooklm-mcp-cli
Version: 0.2.10
Summary: Unified CLI and MCP server for Google NotebookLM
Project-URL: Homepage, https://github.com/jacob-bd/notebooklm-mcp-cli
Project-URL: Repository, https://github.com/jacob-bd/notebooklm-mcp-cli
Project-URL: Issues, https://github.com/jacob-bd/notebooklm-mcp-cli/issues
Author: Jacob Ben-David
License-Expression: MIT
License-File: LICENSE
Keywords: ai,cli,google,mcp,notebooklm,podcast,research
Classifier: Development Status :: 4 - Beta
Classifier: Environment :: Console
Classifier: Intended Audience :: Developers
Classifier: License :: OSI Approved :: MIT License
Classifier: Programming Language :: Python :: 3.11
Classifier: Programming Language :: Python :: 3.12
Classifier: Programming Language :: Python :: 3.13
Requires-Python: >=3.11
Requires-Dist: fastmcp>=0.1.0
Requires-Dist: httpx>=0.27.0
Requires-Dist: platformdirs>=4.0.0
Requires-Dist: pydantic>=2.0.0
Requires-Dist: rich>=13.0.0
Requires-Dist: typer>=0.9.0
Requires-Dist: websocket-client>=1.6.0
Provides-Extra: dev
Requires-Dist: mypy>=1.0.0; extra == 'dev'
Requires-Dist: pytest-asyncio>=0.23.0; extra == 'dev'
Requires-Dist: pytest>=8.0.0; extra == 'dev'
Requires-Dist: ruff>=0.1.0; extra == 'dev'
